{"cameraMode":{"drawMode":0,"name":"Shaded","section":"Shading Mode"},"sceneLighting":true,"audioPlay":false,"sceneViewState":{"m_AlwaysRefresh":false,"showFog":true,"showSkybox":true,"showFlares":true,"showImageEffects":true,"showParticleSystems":true,"showVisualEffectGraphs":true,"m_FxEnabled":true},"in2DMode":false,"pivot":{"x":5.640647888183594,"y":53.30130386352539,"z":102.90103912353516},"rotation":{"x":-0.04981771484017372,"y":0.9340260028839111,"z":-0.14403162896633149,"w":-0.3230612576007843},"size":60.08352279663086,"orthographic":false}